pyvenezuela/__init__.py
pyvenezuela/cache.py
pyvenezuela/decorators.py
pyvenezuela/clients/__init__.py
pyvenezuela/clients/bcv.py
pyvenezuela/clients/cne.py
pyvenezuela/schemas/__init__.py
pyvenezuela/schemas/bcv.py
pyvenezuela/schemas/cache.py
pyvenezuela/schemas/cne.py
pyvenezuela/schemas/persona.py
pyvenezuela-0.0.3.dist-info/LICENSE
pyvenezuela-0.0.3.dist-info/METADATA
pyvenezuela-0.0.3.dist-info/WHEEL
pyvenezuela-0.0.3.dist-info/top_level.txt
pyvenezuela-0.0.3.dist-info/RECORD
