Metadata-Version: 2.1
Name: pyvenezuela
Version: 0.0.3
Summary: Python library that allows querying different Venezuela's data - such as BCV and CNE data.
Home-page: https://github.com/jose2kk/pyvenezuela
Author: Jose Andres Morales
Author-email: jose2kk@gmail.com
Classifier: Programming Language :: Python :: 3
Classifier: Programming Language :: Python :: 3.9
Classifier: Programming Language :: Python :: 3.10
Classifier: Programming Language :: Python :: 3.11
Classifier: License :: OSI Approved :: MIT License
Classifier: Intended Audience :: Developers
Requires-Python: >=3.9
License-File: LICENSE
Requires-Dist: beautifulsoup4 >=4.0
Requires-Dist: pydantic >=2.0
Requires-Dist: requests >=2.0
